[{"Date": "07 August 2024", "Shift Type": "Wednesday AM", "Registrar": "KB"}, {"Date": "07 August 2024", "Shift Type": "Wednesday PM", "Registrar": "SR"}, {"Date": "08 August 2024", "Shift Type": "Thursday AM", "Registrar": "HA"}, {"Date": "08 August 2024", "Shift Type": "Thursday PM", "Registrar": "KK"}, {"Date": "09 August 2024", "Shift Type": "Friday AM", "Registrar": "SH"}, {"Date": "09 August 2024", "Shift Type": "Friday PM", "Registrar": "KP"}, {"Date": "10 August 2024", "Shift Type": "Saturday AM", "Registrar": "KB"}, {"Date": "11 August 2024", "Shift Type": "Sunday AM", "Registrar": "HA"}, {"Date": "12 August 2024", "Shift Type": "Monday AM", "Registrar": "SR"}, {"Date": "12 August 2024", "Shift Type": "Monday PM", "Registrar": "EL"}, {"Date": "13 August 2024", "Shift Type": "Tuesday AM", "Registrar": "HA"}, {"Date": "13 August 2024", "Shift Type": "Tuesday PM", "Registrar": "EL"}, {"Date": "14 August 2024", "Shift Type": "Wednesday AM", "Registrar": "KB"}, {"Date": "14 August 2024", "Shift Type": "Wednesday PM", "Registrar": "SR"}, {"Date": "15 August 2024", "Shift Type": "Thursday AM", "Registrar": "SH"}, {"Date": "15 August 2024", "Shift Type": "Thursday PM", "Registrar": "HA"}, {"Date": "16 August 2024", "Shift Type": "Friday AM", "Registrar": "KB"}, {"Date": "16 August 2024", "Shift Type": "Friday PM", "Registrar": "KP"}, {"Date": "17 August 2024", "Shift Type": "Saturday AM", "Registrar": "HA"}, {"Date": "18 August 2024", "Shift Type": "Sunday AM", "Registrar": "KB"}, {"Date": "19 August 2024", "Shift Type": "Monday AM", "Registrar": "QO"}, {"Date": "19 August 2024", "Shift Type": "Monday PM", "Registrar": "SH"}, {"Date": "20 August 2024", "Shift Type": "Tuesday AM", "Registrar": "EL"}, {"Date": "20 August 2024", "Shift Type": "Tuesday PM", "Registrar": "QO"}, {"Date": "21 August 2024", "Shift Type": "Wednesday AM", "Registrar": "SR"}, {"Date": "21 August 2024", "Shift Type": "Wednesday PM", "Registrar": "KB"}, {"Date": "22 August 2024", "Shift Type": "Thursday AM", "Registrar": "QO"}, {"Date": "22 August 2024", "Shift Type": "Thursday PM", "Registrar": "SR"}, {"Date": "23 August 2024", "Shift Type": "Friday AM", "Registrar": "KB"}, {"Date": "23 August 2024", "Shift Type": "Friday PM", "Registrar": "KP"}, {"Date": "24 August 2024", "Shift Type": "Saturday AM", "Registrar": "SH"}, {"Date": "25 August 2024", "Shift Type": "Sunday AM", "Registrar": "EL"}, {"Date": "26 August 2024", "Shift Type": "Bank Holiday AM", "Registrar": "SR"}, {"Date": "27 August 2024", "Shift Type": "Tuesday AM", "Registrar": "EL"}, {"Date": "27 August 2024", "Shift Type": "Tuesday PM", "Registrar": "QO"}, {"Date": "28 August 2024", "Shift Type": "Wednesday AM", "Registrar": "SR"}, {"Date": "28 August 2024", "Shift Type": "Wednesday PM", "Registrar": "KB"}, {"Date": "29 August 2024", "Shift Type": "Thursday AM", "Registrar": "SH"}, {"Date": "29 August 2024", "Shift Type": "Thursday PM", "Registrar": "HA"}, {"Date": "30 August 2024", "Shift Type": "Friday AM", "Registrar": "KB"}, {"Date": "30 August 2024", "Shift Type": "Friday PM", "Registrar": "KP"}, {"Date": "31 August 2024", "Shift Type": "Saturday AM", "Registrar": "EL"}, {"Date": "01 September 2024", "Shift Type": "Sunday AM", "Registrar": "KP"}, {"Date": "02 September 2024", "Shift Type": "Monday AM", "Registrar": "EL"}, {"Date": "02 September 2024", "Shift Type": "Monday PM", "Registrar": "SH"}, {"Date": "03 September 2024", "Shift Type": "Tuesday AM", "Registrar": "SR"}, {"Date": "03 September 2024", "Shift Type": "Tuesday PM", "Registrar": "EL"}, {"Date": "04 September 2024", "Shift Type": "Wednesday AM", "Registrar": "HA"}, {"Date": "04 September 2024", "Shift Type": "Wednesday PM", "Registrar": "KK"}, {"Date": "05 September 2024", "Shift Type": "Thursday AM", "Registrar": "SR"}, {"Date": "05 September 2024", "Shift Type": "Thursday PM", "Registrar": "QO"}, {"Date": "06 September 2024", "Shift Type": "Friday AM", "Registrar": "SH"}, {"Date": "06 September 2024", "Shift Type": "Friday PM", "Registrar": "KP"}, {"Date": "07 September 2024", "Shift Type": "Saturday AM", "Registrar": "SR"}, {"Date": "08 September 2024", "Shift Type": "Sunday AM", "Registrar": "SH"}, {"Date": "09 September 2024", "Shift Type": "Monday AM", "Registrar": "EL"}, {"Date": "09 September 2024", "Shift Type": "Monday PM", "Registrar": "EL"}, {"Date": "10 September 2024", "Shift Type": "Tuesday AM", "Registrar": "KK"}, {"Date": "10 September 2024", "Shift Type": "Tuesday PM", "Registrar": "HA"}, {"Date": "11 September 2024", "Shift Type": "Wednesday AM", "Registrar": "KB"}, {"Date": "11 September 2024", "Shift Type": "Wednesday PM", "Registrar": "KP"}, {"Date": "12 September 2024", "Shift Type": "Thursday AM", "Registrar": "QO"}, {"Date": "12 September 2024", "Shift Type": "Thursday PM", "Registrar": "SR"}, {"Date": "13 September 2024", "Shift Type": "Friday AM", "Registrar": "HA"}, {"Date": "13 September 2024", "Shift Type": "Friday PM", "Registrar": "KB"}, {"Date": "14 September 2024", "Shift Type": "Saturday AM", "Registrar": "KP"}, {"Date": "15 September 2024", "Shift Type": "Sunday AM", "Registrar": "QO"}, {"Date": "16 September 2024", "Shift Type": "Monday AM", "Registrar": ""}, {"Date": "16 September 2024", "Shift Type": "Monday PM", "Registrar": "QO"}, {"Date": "17 September 2024", "Shift Type": "Tuesday AM", "Registrar": ""}, {"Date": "17 September 2024", "Shift Type": "Tuesday PM", "Registrar": "SR"}, {"Date": "18 September 2024", "Shift Type": "Wednesday AM", "Registrar": ""}, {"Date": "18 September 2024", "Shift Type": "Wednesday PM", "Registrar": "QO"}, {"Date": "19 September 2024", "Shift Type": "Thursday AM", "Registrar": ""}, {"Date": "19 September 2024", "Shift Type": "Thursday PM", "Registrar": "SH"}, {"Date": "20 September 2024", "Shift Type": "Friday AM", "Registrar": ""}, {"Date": "20 September 2024", "Shift Type": "Friday PM", "Registrar": "KP"}, {"Date": "21 September 2024", "Shift Type": "Saturday AM", "Registrar": "SH"}, {"Date": "22 September 2024", "Shift Type": "Sunday AM", "Registrar": "KP"}, {"Date": "23 September 2024", "Shift Type": "Monday AM", "Registrar": ""}, {"Date": "23 September 2024", "Shift Type": "Monday PM", "Registrar": "SR"}, {"Date": "24 September 2024", "Shift Type": "Tuesday AM", "Registrar": ""}, {"Date": "24 September 2024", "Shift Type": "Tuesday PM", "Registrar": "SH"}, {"Date": "25 September 2024", "Shift Type": "Wednesday AM", "Registrar": ""}, {"Date": "25 September 2024", "Shift Type": "Wednesday PM", "Registrar": "SR"}, {"Date": "26 September 2024", "Shift Type": "Thursday AM", "Registrar": ""}, {"Date": "26 September 2024", "Shift Type": "Thursday PM", "Registrar": "SH"}, {"Date": "27 September 2024", "Shift Type": "Friday AM", "Registrar": ""}, {"Date": "27 September 2024", "Shift Type": "Friday PM", "Registrar": "KP"}, {"Date": "28 September 2024", "Shift Type": "Saturday AM", "Registrar": "SR"}, {"Date": "29 September 2024", "Shift Type": "Sunday AM", "Registrar": "KP"}, {"Date": "30 September 2024", "Shift Type": "Monday AM", "Registrar": ""}, {"Date": "30 September 2024", "Shift Type": "Monday PM", "Registrar": "KP"}, {"Date": "01 October 2024", "Shift Type": "Tuesday AM", "Registrar": ""}, {"Date": "01 October 2024", "Shift Type": "Tuesday PM", "Registrar": "SH"}, {"Date": "02 October 2024", "Shift Type": "Wednesday AM", "Registrar": ""}, {"Date": "02 October 2024", "Shift Type": "Wednesday PM", "Registrar": "QO"}, {"Date": "03 October 2024", "Shift Type": "Thursday AM", "Registrar": "HA"}, {"Date": "03 October 2024", "Shift Type": "Thursday PM", "Registrar": ""}, {"Date": "04 October 2024", "Shift Type": "Friday AM", "Registrar": "KB"}, {"Date": "04 October 2024", "Shift Type": "Friday PM", "Registrar": "SH"}, {"Date": "05 October 2024", "Shift Type": "Saturday AM", "Registrar": "QO"}, {"Date": "06 October 2024", "Shift Type": "Sunday AM", "Registrar": "SR"}, {"Date": "07 October 2024", "Shift Type": "Monday AM", "Registrar": "EL"}, {"Date": "07 October 2024", "Shift Type": "Monday PM", "Registrar": "QO"}, {"Date": "08 October 2024", "Shift Type": "Tuesday AM", "Registrar": "KK"}, {"Date": "08 October 2024", "Shift Type": "Tuesday PM", "Registrar": "KK"}, {"Date": "09 October 2024", "Shift Type": "Wednesday AM", "Registrar": "KB"}, {"Date": "09 October 2024", "Shift Type": "Wednesday PM", "Registrar": "QO"}, {"Date": "10 October 2024", "Shift Type": "Thursday AM", "Registrar": "KK"}, {"Date": "10 October 2024", "Shift Type": "Thursday PM", "Registrar": "HA"}, {"Date": "11 October 2024", "Shift Type": "Friday AM", "Registrar": "KB"}, {"Date": "11 October 2024", "Shift Type": "Friday PM", "Registrar": "KP"}, {"Date": "12 October 2024", "Shift Type": "Saturday AM", "Registrar": "EL"}, {"Date": "13 October 2024", "Shift Type": "Sunday AM", "Registrar": "KP"}, {"Date": "14 October 2024", "Shift Type": "Monday AM", "Registrar": "KB"}, {"Date": "14 October 2024", "Shift Type": "Monday PM", "Registrar": "SR"}, {"Date": "15 October 2024", "Shift Type": "Tuesday AM", "Registrar": "KK"}, {"Date": "15 October 2024", "Shift Type": "Tuesday PM", "Registrar": "EL"}, {"Date": "16 October 2024", "Shift Type": "Wednesday AM", "Registrar": "EL"}, {"Date": "16 October 2024", "Shift Type": "Wednesday PM", "Registrar": "KK"}, {"Date": "17 October 2024", "Shift Type": "Thursday AM", "Registrar": "QO"}, {"Date": "17 October 2024", "Shift Type": "Thursday PM", "Registrar": "SR"}, {"Date": "18 October 2024", "Shift Type": "Friday AM", "Registrar": "QO"}, {"Date": "18 October 2024", "Shift Type": "Friday PM", "Registrar": "KP"}, {"Date": "19 October 2024", "Shift Type": "Saturday AM", "Registrar": "EL"}, {"Date": "20 October 2024", "Shift Type": "Sunday AM", "Registrar": "KK"}, {"Date": "21 October 2024", "Shift Type": "Monday AM", "Registrar": "KB"}, {"Date": "21 October 2024", "Shift Type": "Monday PM", "Registrar": "SR"}, {"Date": "22 October 2024", "Shift Type": "Tuesday AM", "Registrar": "EL"}, {"Date": "22 October 2024", "Shift Type": "Tuesday PM", "Registrar": "KK"}, {"Date": "23 October 2024", "Shift Type": "Wednesday AM", "Registrar": "KK"}, {"Date": "23 October 2024", "Shift Type": "Wednesday PM", "Registrar": "EL"}, {"Date": "24 October 2024", "Shift Type": "Thursday AM", "Registrar": ""}, {"Date": "24 October 2024", "Shift Type": "Thursday PM", "Registrar": "KK"}, {"Date": "25 October 2024", "Shift Type": "Friday AM", "Registrar": "KK"}, {"Date": "25 October 2024", "Shift Type": "Friday PM", "Registrar": "KP"}, {"Date": "26 October 2024", "Shift Type": "Saturday AM", "Registrar": "KB"}, {"Date": "27 October 2024", "Shift Type": "Sunday AM", "Registrar": "KP"}, {"Date": "28 October 2024", "Shift Type": "Monday AM", "Registrar": ""}, {"Date": "28 October 2024", "Shift Type": "Monday PM", "Registrar": "KB"}, {"Date": "29 October 2024", "Shift Type": "Tuesday AM", "Registrar": "EL"}, {"Date": "29 October 2024", "Shift Type": "Tuesday PM", "Registrar": "QO"}, {"Date": "30 October 2024", "Shift Type": "Wednesday AM", "Registrar": "KK"}, {"Date": "30 October 2024", "Shift Type": "Wednesday PM", "Registrar": "EL"}, {"Date": "31 October 2024", "Shift Type": "Thursday AM", "Registrar": ""}, {"Date": "31 October 2024", "Shift Type": "Thursday PM", "Registrar": "QO"}, {"Date": "01 November 2024", "Shift Type": "Friday AM", "Registrar": ""}, {"Date": "01 November 2024", "Shift Type": "Friday PM", "Registrar": "KA"}, {"Date": "02 November 2024", "Shift Type": "Saturday AM", "Registrar": "QO"}, {"Date": "03 November 2024", "Shift Type": "Sunday AM", "Registrar": "KB"}, {"Date": "04 November 2024", "Shift Type": "Monday AM", "Registrar": ""}, {"Date": "04 November 2024", "Shift Type": "Monday PM", "Registrar": "KB"}, {"Date": "05 November 2024", "Shift Type": "Tuesday AM", "Registrar": "EL"}, {"Date": "05 November 2024", "Shift Type": "Tuesday PM", "Registrar": "KK"}, {"Date": "06 November 2024", "Shift Type": "Wednesday AM", "Registrar": "KK"}, {"Date": "06 November 2024", "Shift Type": "Wednesday PM", "Registrar": "EL"}, {"Date": "07 November 2024", "Shift Type": "Thursday AM", "Registrar": "QO"}, {"Date": "07 November 2024", "Shift Type": "Thursday PM", "Registrar": "SH"}, {"Date": "08 November 2024", "Shift Type": "Friday AM", "Registrar": "SR"}, {"Date": "08 November 2024", "Shift Type": "Friday PM", "Registrar": "KP"}, {"Date": "09 November 2024", "Shift Type": "Saturday AM", "Registrar": "KK"}, {"Date": "10 November 2024", "Shift Type": "Sunday AM", "Registrar": "KP"}, {"Date": "11 November 2024", "Shift Type": "Monday AM", "Registrar": "SH"}, {"Date": "11 November 2024", "Shift Type": "Monday PM", "Registrar": "KB"}, {"Date": "12 November 2024", "Shift Type": "Tuesday AM", "Registrar": "HA"}, {"Date": "12 November 2024", "Shift Type": "Tuesday PM", "Registrar": "EL"}, {"Date": "13 November 2024", "Shift Type": "Wednesday AM", "Registrar": "KK"}, {"Date": "13 November 2024", "Shift Type": "Wednesday PM", "Registrar": "HA"}, {"Date": "14 November 2024", "Shift Type": "Thursday AM", "Registrar": "QO"}, {"Date": "14 November 2024", "Shift Type": "Thursday PM", "Registrar": "SR"}, {"Date": "15 November 2024", "Shift Type": "Friday AM", "Registrar": "SR"}, {"Date": "15 November 2024", "Shift Type": "Friday PM", "Registrar": "KP"}, {"Date": "16 November 2024", "Shift Type": "Saturday AM", "Registrar": "HA"}, {"Date": "17 November 2024", "Shift Type": "Sunday AM", "Registrar": "SH"}, {"Date": "18 November 2024", "Shift Type": "Monday AM", "Registrar": "SH"}, {"Date": "18 November 2024", "Shift Type": "Monday PM", "Registrar": "KB"}, {"Date": "19 November 2024", "Shift Type": "Tuesday AM", "Registrar": "EL"}, {"Date": "19 November 2024", "Shift Type": "Tuesday PM", "Registrar": "KK"}, {"Date": "20 November 2024", "Shift Type": "Wednesday AM", "Registrar": "KK"}, {"Date": "20 November 2024", "Shift Type": "Wednesday PM", "Registrar": "EL"}, {"Date": "21 November 2024", "Shift Type": "Thursday AM", "Registrar": "QO"}, {"Date": "21 November 2024", "Shift Type": "Thursday PM", "Registrar": "SH"}, {"Date": "22 November 2024", "Shift Type": "Friday AM", "Registrar": "SR"}, {"Date": "22 November 2024", "Shift Type": "Friday PM", "Registrar": "KP"}, {"Date": "23 November 2024", "Shift Type": "Saturday AM", "Registrar": "QO"}, {"Date": "24 November 2024", "Shift Type": "Sunday AM", "Registrar": "HA"}, {"Date": "25 November 2024", "Shift Type": "Monday AM", "Registrar": "SH"}, {"Date": "25 November 2024", "Shift Type": "Monday PM", "Registrar": "KB"}, {"Date": "26 November 2024", "Shift Type": "Tuesday AM", "Registrar": "HA"}, {"Date": "26 November 2024", "Shift Type": "Tuesday PM", "Registrar": "EL"}, {"Date": "27 November 2024", "Shift Type": "Wednesday AM", "Registrar": "KK"}, {"Date": "27 November 2024", "Shift Type": "Wednesday PM", "Registrar": "HA"}, {"Date": "28 November 2024", "Shift Type": "Thursday AM", "Registrar": "SH"}, {"Date": "28 November 2024", "Shift Type": "Thursday PM", "Registrar": "QO"}, {"Date": "29 November 2024", "Shift Type": "Friday AM", "Registrar": "QO"}, {"Date": "29 November 2024", "Shift Type": "Friday PM", "Registrar": "KP"}, {"Date": "30 November 2024", "Shift Type": "Saturday AM", "Registrar": "KK"}, {"Date": "01 December 2024", "Shift Type": "Sunday AM", "Registrar": "EL"}, {"Date": "02 December 2024", "Shift Type": "Monday AM", "Registrar": ""}, {"Date": "02 December 2024", "Shift Type": "Monday PM", "Registrar": "KB"}, {"Date": "03 December 2024", "Shift Type": "Tuesday AM", "Registrar": "HA"}, {"Date": "03 December 2024", "Shift Type": "Tuesday PM", "Registrar": "EL"}, {"Date": "04 December 2024", "Shift Type": "Wednesday AM", "Registrar": "KK"}, {"Date": "04 December 2024", "Shift Type": "Wednesday PM", "Registrar": "HA"}, {"Date": "05 December 2024", "Shift Type": "Thursday AM", "Registrar": "KA"}, {"Date": "05 December 2024", "Shift Type": "Thursday PM", "Registrar": "QO"}, {"Date": "06 December 2024", "Shift Type": "Friday AM", "Registrar": "QO"}, {"Date": "06 December 2024", "Shift Type": "Friday PM", "Registrar": "KP"}, {"Date": "07 December 2024", "Shift Type": "Saturday AM", "Registrar": "QO"}, {"Date": "08 December 2024", "Shift Type": "Sunday AM", "Registrar": "HA"}, {"Date": "09 December 2024", "Shift Type": "Monday AM", "Registrar": ""}, {"Date": "09 December 2024", "Shift Type": "Monday PM", "Registrar": "KB"}, {"Date": "10 December 2024", "Shift Type": "Tuesday AM", "Registrar": "KK"}, {"Date": "10 December 2024", "Shift Type": "Tuesday PM", "Registrar": "EL"}, {"Date": "11 December 2024", "Shift Type": "Wednesday AM", "Registrar": "EL"}, {"Date": "11 December 2024", "Shift Type": "Wednesday PM", "Registrar": "KK"}, {"Date": "12 December 2024", "Shift Type": "Thursday AM", "Registrar": "HA"}, {"Date": "12 December 2024", "Shift Type": "Thursday PM", "Registrar": "SR"}, {"Date": "13 December 2024", "Shift Type": "Friday AM", "Registrar": ""}, {"Date": "13 December 2024", "Shift Type": "Friday PM", "Registrar": "SR"}, {"Date": "14 December 2024", "Shift Type": "Saturday AM", "Registrar": "KK"}, {"Date": "15 December 2024", "Shift Type": "Sunday AM", "Registrar": "SR"}, {"Date": "16 December 2024", "Shift Type": "Monday AM", "Registrar": "KA"}, {"Date": "16 December 2024", "Shift Type": "Monday PM", "Registrar": "KB"}, {"Date": "17 December 2024", "Shift Type": "Tuesday AM", "Registrar": "HA"}, {"Date": "17 December 2024", "Shift Type": "Tuesday PM", "Registrar": "EL"}, {"Date": "18 December 2024", "Shift Type": "Wednesday AM", "Registrar": "EL"}, {"Date": "18 December 2024", "Shift Type": "Wednesday PM", "Registrar": "HA"}, {"Date": "19 December 2024", "Shift Type": "Thursday AM", "Registrar": "KA"}, {"Date": "19 December 2024", "Shift Type": "Thursday PM", "Registrar": "SR"}, {"Date": "20 December 2024", "Shift Type": "Friday AM", "Registrar": "SR"}, {"Date": "20 December 2024", "Shift Type": "Friday PM", "Registrar": "KP"}, {"Date": "21 December 2024", "Shift Type": "Saturday AM", "Registrar": "KB"}, {"Date": "22 December 2024", "Shift Type": "Sunday AM", "Registrar": "EL"}, {"Date": "23 December 2024", "Shift Type": "Monday AM", "Registrar": "KA"}, {"Date": "23 December 2024", "Shift Type": "Monday PM", "Registrar": "QO"}, {"Date": "24 December 2024", "Shift Type": "Tuesday AM", "Registrar": "HA"}, {"Date": "24 December 2024", "Shift Type": "Tuesday PM", "Registrar": "EL"}, {"Date": "25 December 2024", "Shift Type": "Bank Holiday AM", "Registrar": "QO"}, {"Date": "26 December 2024", "Shift Type": "Bank Holiday AM", "Registrar": "EL"}, {"Date": "27 December 2024", "Shift Type": "Friday AM", "Registrar": "QO"}, {"Date": "27 December 2024", "Shift Type": "Friday PM", "Registrar": "KP"}, {"Date": "28 December 2024", "Shift Type": "Saturday AM", "Registrar": "SR"}, {"Date": "29 December 2024", "Shift Type": "Sunday AM", "Registrar": "KP"}, {"Date": "30 December 2024", "Shift Type": "Monday AM", "Registrar": "KA"}, {"Date": "30 December 2024", "Shift Type": "Monday PM", "Registrar": "SR"}, {"Date": "31 December 2024", "Shift Type": "Tuesday AM", "Registrar": "EL"}, {"Date": "31 December 2024", "Shift Type": "Tuesday PM", "Registrar": "HA"}, {"Date": "01 January 2025", "Shift Type": "Bank Holiday AM", "Registrar": "SR"}, {"Date": "02 January 2025", "Shift Type": "Thursday AM", "Registrar": "QO"}, {"Date": "02 January 2025", "Shift Type": "Thursday PM", "Registrar": "SR"}, {"Date": "03 January 2025", "Shift Type": "Friday AM", "Registrar": "KA"}, {"Date": "03 January 2025", "Shift Type": "Friday PM", "Registrar": "KP"}, {"Date": "04 January 2025", "Shift Type": "Saturday AM", "Registrar": "QO"}, {"Date": "05 January 2025", "Shift Type": "Sunday AM", "Registrar": "KK"}, {"Date": "06 January 2025", "Shift Type": "Monday AM", "Registrar": "QO"}, {"Date": "06 January 2025", "Shift Type": "Monday PM", "Registrar": "KB"}, {"Date": "07 January 2025", "Shift Type": "Tuesday AM", "Registrar": "HA"}, {"Date": "07 January 2025", "Shift Type": "Tuesday PM", "Registrar": "EL"}, {"Date": "08 January 2025", "Shift Type": "Wednesday AM", "Registrar": "EL"}, {"Date": "08 January 2025", "Shift Type": "Wednesday PM", "Registrar": "KA"}, {"Date": "09 January 2025", "Shift Type": "Thursday AM", "Registrar": "KA"}, {"Date": "09 January 2025", "Shift Type": "Thursday PM", "Registrar": "QO"}, {"Date": "10 January 2025", "Shift Type": "Friday AM", "Registrar": "KK"}, {"Date": "10 January 2025", "Shift Type": "Friday PM", "Registrar": "SR"}, {"Date": "11 January 2025", "Shift Type": "Saturday AM", "Registrar": "EL"}, {"Date": "12 January 2025", "Shift Type": "Sunday AM", "Registrar": ""}, {"Date": "13 January 2025", "Shift Type": "Monday AM", "Registrar": "SR"}, {"Date": "13 January 2025", "Shift Type": "Monday PM", "Registrar": "QO"}, {"Date": "14 January 2025", "Shift Type": "Tuesday AM", "Registrar": "HA"}, {"Date": "14 January 2025", "Shift Type": "Tuesday PM", "Registrar": "EL"}, {"Date": "15 January 2025", "Shift Type": "Wednesday AM", "Registrar": ""}, {"Date": "15 January 2025", "Shift Type": "Wednesday PM", "Registrar": "HA"}, {"Date": "16 January 2025", "Shift Type": "Thursday AM", "Registrar": "QO"}, {"Date": "16 January 2025", "Shift Type": "Thursday PM", "Registrar": "SR"}, {"Date": "17 January 2025", "Shift Type": "Friday AM", "Registrar": "SR"}, {"Date": "17 January 2025", "Shift Type": "Friday PM", "Registrar": "KB"}, {"Date": "18 January 2025", "Shift Type": "Saturday AM", "Registrar": "KB"}, {"Date": "19 January 2025", "Shift Type": "Sunday AM", "Registrar": "QO"}, {"Date": "20 January 2025", "Shift Type": "Monday AM", "Registrar": "KA"}, {"Date": "20 January 2025", "Shift Type": "Monday PM", "Registrar": "SR"}, {"Date": "21 January 2025", "Shift Type": "Tuesday AM", "Registrar": "SR"}, {"Date": "21 January 2025", "Shift Type": "Tuesday PM", "Registrar": "HA"}, {"Date": "22 January 2025", "Shift Type": "Wednesday AM", "Registrar": "HA"}, {"Date": "22 January 2025", "Shift Type": "Wednesday PM", "Registrar": "EL"}, {"Date": "23 January 2025", "Shift Type": "Thursday AM", "Registrar": "KA"}, {"Date": "23 January 2025", "Shift Type": "Thursday PM", "Registrar": "QO"}, {"Date": "24 January 2025", "Shift Type": "Friday AM", "Registrar": "SR"}, {"Date": "24 January 2025", "Shift Type": "Friday PM", "Registrar": "KA"}, {"Date": "25 January 2025", "Shift Type": "Saturday AM", "Registrar": "KP"}, {"Date": "26 January 2025", "Shift Type": "Sunday AM", "Registrar": "HA"}, {"Date": "27 January 2025", "Shift Type": "Monday AM", "Registrar": "QO"}, {"Date": "27 January 2025", "Shift Type": "Monday PM", "Registrar": "KA"}, {"Date": "28 January 2025", "Shift Type": "Tuesday AM", "Registrar": "HA"}, {"Date": "28 January 2025", "Shift Type": "Tuesday PM", "Registrar": "EL"}, {"Date": "29 January 2025", "Shift Type": "Wednesday AM", "Registrar": "SR"}, {"Date": "29 January 2025", "Shift Type": "Wednesday PM", "Registrar": "HA"}, {"Date": "30 January 2025", "Shift Type": "Thursday AM", "Registrar": "KA"}, {"Date": "30 January 2025", "Shift Type": "Thursday PM", "Registrar": "QO"}, {"Date": "31 January 2025", "Shift Type": "Friday AM", "Registrar": "QO"}, {"Date": "31 January 2025", "Shift Type": "Friday PM", "Registrar": "SR"}, {"Date": "01 February 2025", "Shift Type": "Saturday AM", "Registrar": "KK"}, {"Date": "02 February 2025", "Shift Type": "Sunday AM", "Registrar": "KK"}, {"Date": "03 February 2025", "Shift Type": "Monday AM", "Registrar": "SR"}, {"Date": "03 February 2025", "Shift Type": "Monday PM", "Registrar": "KB"}, {"Date": "04 February 2025", "Shift Type": "Tuesday AM", "Registrar": "KA"}, {"Date": "04 February 2025", "Shift Type": "Tuesday PM", "Registrar": "HA"}, {"Date": "05 February 2025", "Shift Type": "Wednesday AM", "Registrar": "HA"}, {"Date": "05 February 2025", "Shift Type": "Wednesday PM", "Registrar": "SR"}, {"Date": "06 February 2025", "Shift Type": "Thursday AM", "Registrar": "KA"}, {"Date": "06 February 2025", "Shift Type": "Thursday PM", "Registrar": ""}, {"Date": "07 February 2025", "Shift Type": "Friday AM", "Registrar": "KA"}, {"Date": "07 February 2025", "Shift Type": "Friday PM", "Registrar": "SR"}, {"Date": "08 February 2025", "Shift Type": "Saturday AM", "Registrar": "MM"}, {"Date": "09 February 2025", "Shift Type": "Sunday AM", "Registrar": "HA"}, {"Date": "10 February 2025", "Shift Type": "Monday AM", "Registrar": "MM"}, {"Date": "10 February 2025", "Shift Type": "Monday PM", "Registrar": "KB"}, {"Date": "11 February 2025", "Shift Type": "Tuesday AM", "Registrar": "MM"}, {"Date": "11 February 2025", "Shift Type": "Tuesday PM", "Registrar": "EL"}, {"Date": "12 February 2025", "Shift Type": "Wednesday AM", "Registrar": "EL"}, {"Date": "12 February 2025", "Shift Type": "Wednesday PM", "Registrar": "SR"}, {"Date": "13 February 2025", "Shift Type": "Thursday AM", "Registrar": "KA"}, {"Date": "13 February 2025", "Shift Type": "Thursday PM", "Registrar": "MM"}, {"Date": "14 February 2025", "Shift Type": "Friday AM", "Registrar": "KA"}, {"Date": "14 February 2025", "Shift Type": "Friday PM", "Registrar": "HA"}, {"Date": "15 February 2025", "Shift Type": "Saturday AM", "Registrar": "KB"}, {"Date": "16 February 2025", "Shift Type": "Sunday AM", "Registrar": "EL"}, {"Date": "17 February 2025", "Shift Type": "Monday AM", "Registrar": "KA"}, {"Date": "17 February 2025", "Shift Type": "Monday PM", "Registrar": "KB"}, {"Date": "18 February 2025", "Shift Type": "Tuesday AM", "Registrar": "SR"}, {"Date": "18 February 2025", "Shift Type": "Tuesday PM", "Registrar": "EL"}, {"Date": "19 February 2025", "Shift Type": "Wednesday AM", "Registrar": "EL"}, {"Date": "19 February 2025", "Shift Type": "Wednesday PM", "Registrar": "HA"}, {"Date": "20 February 2025", "Shift Type": "Thursday AM", "Registrar": "QO"}, {"Date": "20 February 2025", "Shift Type": "Thursday PM", "Registrar": "SR"}, {"Date": "21 February 2025", "Shift Type": "Friday AM", "Registrar": "QO"}, {"Date": "21 February 2025", "Shift Type": "Friday PM", "Registrar": "MM"}, {"Date": "22 February 2025", "Shift Type": "Saturday AM", "Registrar": "KP"}, {"Date": "23 February 2025", "Shift Type": "Sunday AM", "Registrar": "QO"}, {"Date": "24 February 2025", "Shift Type": "Monday AM", "Registrar": "SR"}, {"Date": "24 February 2025", "Shift Type": "Monday PM", "Registrar": "QO"}, {"Date": "25 February 2025", "Shift Type": "Tuesday AM", "Registrar": "HA"}, {"Date": "25 February 2025", "Shift Type": "Tuesday PM", "Registrar": "EL"}, {"Date": "26 February 2025", "Shift Type": "Wednesday AM", "Registrar": "EL"}, {"Date": "26 February 2025", "Shift Type": "Wednesday PM", "Registrar": "HA"}, {"Date": "27 February 2025", "Shift Type": "Thursday AM", "Registrar": "MM"}, {"Date": "27 February 2025", "Shift Type": "Thursday PM", "Registrar": "SR"}, {"Date": "28 February 2025", "Shift Type": "Friday AM", "Registrar": "SR"}, {"Date": "28 February 2025", "Shift Type": "Friday PM", "Registrar": "MM"}, {"Date": "01 March 2025", "Shift Type": "Saturday AM", "Registrar": "SR"}, {"Date": "02 March 2025", "Shift Type": "Sunday AM", "Registrar": "SR"}, {"Date": "03 March 2025", "Shift Type": "Monday AM", "Registrar": "MM"}, {"Date": "03 March 2025", "Shift Type": "Monday PM", "Registrar": "QO"}, {"Date": "04 March 2025", "Shift Type": "Tuesday AM", "Registrar": "HA"}, {"Date": "04 March 2025", "Shift Type": "Tuesday PM", "Registrar": "EL"}, {"Date": "05 March 2025", "Shift Type": "Wednesday AM", "Registrar": "EL"}, {"Date": "05 March 2025", "Shift Type": "Wednesday PM", "Registrar": "HA"}, {"Date": "06 March 2025", "Shift Type": "Thursday AM", "Registrar": "SH"}, {"Date": "06 March 2025", "Shift Type": "Thursday PM", "Registrar": "MM"}, {"Date": "07 March 2025", "Shift Type": "Friday AM", "Registrar": "MM"}, {"Date": "07 March 2025", "Shift Type": "Friday PM", "Registrar": "SR"}, {"Date": "08 March 2025", "Shift Type": "Saturday AM", "Registrar": "SH"}, {"Date": "09 March 2025", "Shift Type": "Sunday AM", "Registrar": "MM"}, {"Date": "10 March 2025", "Shift Type": "Monday AM", "Registrar": "SH"}, {"Date": "10 March 2025", "Shift Type": "Monday PM", "Registrar": "KB"}, {"Date": "11 March 2025", "Shift Type": "Tuesday AM", "Registrar": "HA"}, {"Date": "11 March 2025", "Shift Type": "Tuesday PM", "Registrar": "MM"}, {"Date": "12 March 2025", "Shift Type": "Wednesday AM", "Registrar": "MM"}, {"Date": "12 March 2025", "Shift Type": "Wednesday PM", "Registrar": "HA"}, {"Date": "13 March 2025", "Shift Type": "Thursday AM", "Registrar": "SH"}, {"Date": "13 March 2025", "Shift Type": "Thursday PM", "Registrar": "SR"}, {"Date": "14 March 2025", "Shift Type": "Friday AM", "Registrar": "SR"}, {"Date": "14 March 2025", "Shift Type": "Friday PM", "Registrar": "QO"}, {"Date": "15 March 2025", "Shift Type": "Saturday AM", "Registrar": "HA"}, {"Date": "16 March 2025", "Shift Type": "Sunday AM", "Registrar": "KB"}, {"Date": "17 March 2025", "Shift Type": "Monday AM", "Registrar": "MM"}, {"Date": "17 March 2025", "Shift Type": "Monday PM", "Registrar": "KB"}, {"Date": "18 March 2025", "Shift Type": "Tuesday AM", "Registrar": "MM"}, {"Date": "18 March 2025", "Shift Type": "Tuesday PM", "Registrar": "HA"}, {"Date": "19 March 2025", "Shift Type": "Wednesday AM", "Registrar": "HA"}, {"Date": "19 March 2025", "Shift Type": "Wednesday PM", "Registrar": "KA"}, {"Date": "20 March 2025", "Shift Type": "Thursday AM", "Registrar": "SH"}, {"Date": "20 March 2025", "Shift Type": "Thursday PM", "Registrar": "QO"}, {"Date": "21 March 2025", "Shift Type": "Friday AM", "Registrar": "MM"}, {"Date": "21 March 2025", "Shift Type": "Friday PM", "Registrar": "SR"}, {"Date": "22 March 2025", "Shift Type": "Saturday AM", "Registrar": "QO"}, {"Date": "23 March 2025", "Shift Type": "Sunday AM", "Registrar": "KP"}, {"Date": "24 March 2025", "Shift Type": "Monday AM", "Registrar": "MM"}, {"Date": "24 March 2025", "Shift Type": "Monday PM", "Registrar": "KB"}, {"Date": "25 March 2025", "Shift Type": "Tuesday AM", "Registrar": "HA"}, {"Date": "25 March 2025", "Shift Type": "Tuesday PM", "Registrar": "SR"}, {"Date": "26 March 2025", "Shift Type": "Wednesday AM", "Registrar": "KA"}, {"Date": "26 March 2025", "Shift Type": "Wednesday PM", "Registrar": "MM"}, {"Date": "27 March 2025", "Shift Type": "Thursday AM", "Registrar": "MM"}, {"Date": "27 March 2025", "Shift Type": "Thursday PM", "Registrar": "QO"}, {"Date": "28 March 2025", "Shift Type": "Friday AM", "Registrar": "QO"}, {"Date": "28 March 2025", "Shift Type": "Friday PM", "Registrar": "KA"}, {"Date": "29 March 2025", "Shift Type": "Saturday AM", "Registrar": "SR"}, {"Date": "30 March 2025", "Shift Type": "Sunday AM", "Registrar": "EL"}]